elevenlabs_tts_tool/__init__.py
elevenlabs_tts_tool/cli.py
elevenlabs_tts_tool/logging_config.py
elevenlabs_tts_tool/models.py
elevenlabs_tts_tool/utils.py
elevenlabs_tts_tool/voices.py
elevenlabs_tts_tool/voices_lookup.json
elevenlabs_tts_tool/commands/__init__.py
elevenlabs_tts_tool/commands/completion_commands.py
elevenlabs_tts_tool/commands/info_commands.py
elevenlabs_tts_tool/commands/model_commands.py
elevenlabs_tts_tool/commands/synthesize_commands.py
elevenlabs_tts_tool/commands/update_voices_commands.py
elevenlabs_tts_tool/commands/voice_commands.py
elevenlabs_tts_tool/core/__init__.py
elevenlabs_tts_tool/core/client.py
elevenlabs_tts_tool/core/synthesize.py
elevenlabs_tts_tool-0.2.0.dist-info/METADATA
elevenlabs_tts_tool-0.2.0.dist-info/WHEEL
elevenlabs_tts_tool-0.2.0.dist-info/entry_points.txt
elevenlabs_tts_tool-0.2.0.dist-info/licenses/LICENSE
elevenlabs_tts_tool-0.2.0.dist-info/RECORD
