Metadata-Version: 2.4
Name: elevenlabs-tts-tool
Version: 0.2.0
Summary: Professional command-line tool for ElevenLabs text-to-speech synthesis
Project-URL: Homepage, https://github.com/dnvriend/elevenlabs-tts-tool
Project-URL: Repository, https://github.com/dnvriend/elevenlabs-tts-tool
Project-URL: Issues, https://github.com/dnvriend/elevenlabs-tts-tool/issues
Project-URL: Changelog, https://github.com/dnvriend/elevenlabs-tts-tool/releases
Author-email: Dennis Vriend <dvriend@ilionx.com>
License: MIT
License-File: LICENSE
Keywords: ai-voice,cli,command-line,elevenlabs,speech-synthesis,text-to-speech,tts,voice-generation
Classifier: Development Status :: 4 - Beta
Classifier: Environment :: Console
Classifier: Intended Audience :: Developers
Classifier: Intended Audience :: End Users/Desktop
Classifier: License :: OSI Approved :: MIT License
Classifier: Operating System :: OS Independent
Classifier: Programming Language :: Python :: 3
Classifier: Programming Language :: Python :: 3.13
Classifier: Programming Language :: Python :: 3.14
Classifier: Topic :: Multimedia :: Sound/Audio :: Speech
Classifier: Topic :: Software Development :: Libraries :: Python Modules
Classifier: Topic :: Utilities
Classifier: Typing :: Typed
Requires-Python: >=3.13
Requires-Dist: click>=8.1.7
Requires-Dist: elevenlabs>=1.0.0
Requires-Dist: urllib3>=2.6.0
